NEURON_gpu_nightly-9.0.dev1289.dist-info/METADATA
NEURON_gpu_nightly-9.0.dev1289.dist-info/WHEEL
NEURON_gpu_nightly-9.0.dev1289.dist-info/top_level.txt
NEURON_gpu_nightly-9.0.dev1289.dist-info/RECORD
NEURON_gpu_nightly-9.0.dev1289.data/scripts/modlunit
NEURON_gpu_nightly-9.0.dev1289.data/scripts/idraw
NEURON_gpu_nightly-9.0.dev1289.data/scripts/mkthreadsafe
NEURON_gpu_nightly-9.0.dev1289.data/scripts/nrniv-core
NEURON_gpu_nightly-9.0.dev1289.data/scripts/nrnivmodl
NEURON_gpu_nightly-9.0.dev1289.data/scripts/nrngui
NEURON_gpu_nightly-9.0.dev1289.data/scripts/nrnivmodl-core
NEURON_gpu_nightly-9.0.dev1289.data/scripts/nrniv
NEURON_gpu_nightly-9.0.dev1289.data/scripts/nrnpyenv.sh
NEURON_gpu_nightly-9.0.dev1289.data/scripts/sortspike
NEURON_gpu_nightly-9.0.dev1289.data/scripts/neurondemo
NEURON_gpu_nightly.libs/libcudadevice-5901c3a2.so
NEURON_gpu_nightly.libs/libnvomp-fb1a2b9f.so
NEURON_gpu_nightly.libs/libcudanvhpc-8257c6fc.so
NEURON_gpu_nightly.libs/libacchost-c31344de.so
NEURON_gpu_nightly.libs/libnvhpcatm-406400d8.so
NEURON_gpu_nightly.libs/libnvc-ca879ffd.so
NEURON_gpu_nightly.libs/libaccdevaux-f0c679c6.so
NEURON_gpu_nightly.libs/libnvcpumath-avx2-91375214.so
NEURON_gpu_nightly.libs/libcoreneuron-cuda-5314dd88.so
NEURON_gpu_nightly.libs/libcudart-4554289f.so.11.5.117
NEURON_gpu_nightly.libs/libacccuda-43e350a6.so
neuron/units.py
neuron/config.py
neuron/expect_hocerr.py
neuron/__init__.py
neuron/hclass3.py
neuron/help_data.dat
neuron/sections.py
neuron/nonvint_block_supervisor.py
neuron/hoc.cpython-311-x86_64-linux-gnu.so
neuron/coreneuron.py
neuron/psection.py
neuron/doc.py
neuron/gui.py
neuron/.data/bin/nocmodl
neuron/.data/bin/modlunit
neuron/.data/bin/idraw
neuron/.data/bin/mkthreadsafe
neuron/.data/bin/idemo
neuron/.data/bin/nrnmech_makefile
neuron/.data/bin/nrniv-core
neuron/.data/bin/nrnivmodl
neuron/.data/bin/set_nrnpyenv.sh
neuron/.data/bin/iclass
neuron/.data/bin/nrngui
neuron/.data/bin/nrnivmodl-core
neuron/.data/bin/nrniv
neuron/.data/bin/nrnpyenv.sh
neuron/.data/bin/sortspike
neuron/.data/bin/neurondemo
neuron/.data/bin/mod2c_core
neuron/.data/lib/libnrnpython3.so
