Metadata-Version: 2.1
Name: NEURON-gpu-nightly
Version: 9.0.dev1289
Summary: Empirically-based simulator for modeling neurons and networks of neurons
Home-page: https://neuron.yale.edu/neuron/
Author: Michael Hines, Yale, Blue Brain Project
Author-email: michael.hines@yale.edu
Maintainer: Michael Hines
License: Copyright (c) Michael Hines (BSD compatible)
Project-URL: Source, https://github.com/neuronsimulator/nrn
Classifier: Programming Language :: C++
Classifier: Programming Language :: Python
Classifier: Topic :: Scientific/Engineering
Classifier: License :: Other/Proprietary License
Requires-Dist: numpy (>=1.9.3)
Requires-Dist: patchelf
